{"city": "Ignace", "country": "CA", "elevation_ft": 1435, "elevation_m": 437, "iata": "ZUC", "icao": "CZUC", "latitude": 49.4296989440918, "longitude": -91.7177963256836, "name": "Ignace Municipal Airport", "note": null, "reporting": false, "runways": [{"length_ft": 3512, "width_ft": 75, "surface": "asphalt", "lights": true, "ident1": "05", "ident2": "23", "bearing1": 49.3, "bearing2": 229.3}], "state": "ON", "type": "medium_airport", "website": null, "wiki": "https://en.wikipedia.org/wiki/Ignace_Municipal_Airport"}