{"city": "Siglufj\u00f6r\u00f0ur", "country": "IS", "elevation_ft": 10, "elevation_m": 3, "iata": "SIJ", "icao": "BISI", "latitude": 66.137847, "longitude": -18.908157, "name": "Siglufj\u00f6r\u00f0ur Airport", "note": null, "reporting": false, "runways": [{"length_ft": 3556, "width_ft": 105, "surface": "asphalt", "lights": false, "ident1": "07", "ident2": "25", "bearing1": 43.0, "bearing2": 223.0}], "state": "6", "type": "medium_airport", "website": null, "wiki": "https://en.wikipedia.org/wiki/Siglufj%C3%B6r%C3%B0ur_Airport"}