{"city": "Lourdes-De-Blanc-Sablon", "country": "CA", "elevation_ft": 121, "elevation_m": 37, "iata": "YBX", "icao": "CYBX", "latitude": 51.443599700899995, "longitude": -57.185298919699996, "name": "Lourdes de Blanc Sablon Airport", "note": null, "reporting": true, "runways": [{"length_ft": 4500, "width_ft": 150, "surface": "asphalt", "lights": true, "ident1": "05", "ident2": "23", "bearing1": 27.5, "bearing2": 207.5}], "state": "QC", "type": "medium_airport", "website": null, "wiki": "https://en.wikipedia.org/wiki/Lourdes-de-Blanc-Sablon_Airport"}