{"city": "Angelsey", "country": "GB", "elevation_ft": 37, "elevation_m": 11, "iata": "VLY", "icao": "EGOV", "latitude": 53.2481002808, "longitude": -4.53533983231, "name": "Anglesey Airport", "note": "Maes Awyr M\u1ed1n, RAF Valley", "reporting": true, "runways": [{"length_ft": 7513, "width_ft": 151, "surface": "asphalt", "lights": true, "ident1": "13", "ident2": "31", "bearing1": 131.0, "bearing2": 311.0}, {"length_ft": 5377, "width_ft": 151, "surface": "asphalt", "lights": true, "ident1": "01", "ident2": "19", "bearing1": 6.3, "bearing2": 186.3}], "state": "WLS", "type": "medium_airport", "website": "http://www.angleseyairport.com/", "wiki": "https://en.wikipedia.org/wiki/Anglesey_Airport"}